api_logic_server_cli/__init__.py
api_logic_server_cli/api_logic_server.py
api_logic_server_cli/api_logic_server_info.yaml
api_logic_server_cli/cli.py
api_logic_server_cli/cli_args_base.py
api_logic_server_cli/cli_args_project.py
api_logic_server_cli/extended_builder.py
api_logic_server_cli/genai.py
api_logic_server_cli/logging.yml
api_logic_server_cli/manager.py
api_logic_server_cli/create_from_model/__init__.py
api_logic_server_cli/create_from_model/api_expose_api_models_creator.py
api_logic_server_cli/create_from_model/api_logic_server_utils.py
api_logic_server_cli/create_from_model/create_db_from_model.py
api_logic_server_cli/create_from_model/meta_model.py
api_logic_server_cli/create_from_model/model_creation_services.py
api_logic_server_cli/create_from_model/ont_build.py
api_logic_server_cli/create_from_model/ont_create.py
api_logic_server_cli/create_from_model/ui_admin_creator.py
api_logic_server_cli/create_from_model/uri_info.py
api_logic_server_cli/create_from_model/__pycache__/__init__.cpython-312.pyc
api_logic_server_cli/create_from_model/__pycache__/api_expose_api_models_creator.cpython-312.pyc
api_logic_server_cli/create_from_model/__pycache__/api_logic_server_utils.cpython-312.pyc
api_logic_server_cli/create_from_model/__pycache__/create_db_from_model.cpython-312.pyc
api_logic_server_cli/create_from_model/__pycache__/meta_model.cpython-312.pyc
api_logic_server_cli/create_from_model/__pycache__/model_creation_services.cpython-312.pyc
api_logic_server_cli/create_from_model/__pycache__/ont_build.cpython-312.pyc
api_logic_server_cli/create_from_model/__pycache__/ont_create.cpython-312.pyc
api_logic_server_cli/create_from_model/__pycache__/ui_admin_creator.cpython-312.pyc
api_logic_server_cli/create_from_model/__pycache__/uri_info.cpython-312.pyc
api_logic_server_cli/create_from_model/safrs-react-admin-npm-build/asset-manifest.json
api_logic_server_cli/create_from_model/safrs-react-admin-npm-build/favicon.ico
ApiLogicServer-10.4.61.dist-info/LICENSE
ApiLogicServer-10.4.61.dist-info/METADATA
ApiLogicServer-10.4.61.dist-info/WHEEL
ApiLogicServer-10.4.61.dist-info/entry_points.txt
ApiLogicServer-10.4.61.dist-info/top_level.txt
ApiLogicServer-10.4.61.dist-info/RECORD
