Metadata-Version: 2.1
Name: ApiLogicServer
Version: 10.4.61
Author-email: Val Huber <apilogicserver@gmail.com>
License: BSD-3-Clause
Project-URL: Homepage, https://apilogicserver.github.io/Docs/
Project-URL: Source, https://github.com/ApiLogicServer/ApiLogicServer-src
Project-URL: Issues, https://github.com/ApiLogicServer/ApiLogicServer-src/issues
Keywords: Flask,SQLAlchemy,Rules,WebApp,Microservice,ReactAdmin,Angular
Classifier: Development Status :: 5 - Production/Stable
Classifier: Environment :: Web Environment
Classifier: Intended Audience :: Developers
Classifier: License :: OSI Approved :: BSD License
Classifier: Operating System :: OS Independent
Classifier: Programming Language :: Python :: 3.12
Classifier: Programming Language :: Python :: 3.11
Classifier: Programming Language :: Python :: 3.10
Classifier: Programming Language :: Python :: 3.9
Classifier: Programming Language :: Python :: 3.8
Classifier: Topic :: Software Development :: Libraries :: Python Modules
Requires-Python: >=3.8
License-File: LICENSE
Requires-Dist: PyJWT ==2.6.0
Requires-Dist: python-dateutil ==2.8.2
Requires-Dist: SQLAlchemy-Utils ==0.38.2
Requires-Dist: logicbankutils ==0.6.0
Requires-Dist: inflect ==5.0.2
Requires-Dist: Flask ==2.3.2
Requires-Dist: Flask-Cors ==3.0.10
Requires-Dist: Flask-RESTful >=0.3.9
Requires-Dist: flask-restful-swagger-2 >=0.35
Requires-Dist: Flask-SQLAlchemy ==3.0.3
Requires-Dist: flask-swagger-ui >=4.11.1
Requires-Dist: flask-bcrypt ==1.0.1
Requires-Dist: itsdangerous ==2.1.2
Requires-Dist: Jinja2 ==3.1.2
Requires-Dist: MarkupSafe ==2.1.3
Requires-Dist: six ==1.16.0
Requires-Dist: SQLAlchemy ==2.0.15
Requires-Dist: Werkzeug ==2.3.3
Requires-Dist: safrs >=3.1.3
Requires-Dist: Flask-Admin ==1.5.7
Requires-Dist: Flask-JWT-Extended ==4.4.4
Requires-Dist: Flask-Login ==0.6.2
Requires-Dist: Flask-OpenID ==1.3.0
Requires-Dist: python-dotenv ==0.15.0
Requires-Dist: email-validator ==1.1.1
Requires-Dist: LogicBank >=1.20.4
Requires-Dist: cryptography ==36.0.1
Requires-Dist: rsa
Requires-Dist: PyMySQL ==1.0.3
Requires-Dist: oracledb ==2.1.2
Requires-Dist: requests ==2.31.0
Requires-Dist: gunicorn ==20.1.0
Requires-Dist: psycopg2-binary ==2.9.9
Requires-Dist: dotmap ==1.3.25
Requires-Dist: WTForms ==2.3.3
Requires-Dist: behave ==1.2.6
Requires-Dist: alembic ==1.7.7
Requires-Dist: GeoAlchemy2 ==0.12.5
Requires-Dist: confluent-kafka ==2.3.0
Requires-Dist: translate ==3.6.1
Requires-Dist: libretranslatepy ==2.1.1
Requires-Dist: reportlab ==4.2.0
